setup.py
rullet/__init__.py
rullet/command_line.py
rullet/rullet.py
rullet.egg-info/PKG-INFO
rullet.egg-info/SOURCES.txt
rullet.egg-info/dependency_links.txt
rullet.egg-info/entry_points.txt
rullet.egg-info/not-zip-safe
rullet.egg-info/top_level.txt