Metadata-Version: 1.0
Name: rullet
Version: 0.1.2
Summary: Just a script selecting an item from an array randomly
Home-page: http://github.com/minsoopark/Rullet
Author: Minsoo Park
Author-email: minsoo1003@gmail.com
License: MIT
Platform: UNKNOWN
